openthaigpt/__init__.py
openthaigpt/openthaigpt_module.py
openthaigpt-0.1.1.dist-info/AUTHORS.md
openthaigpt-0.1.1.dist-info/LICENSE
openthaigpt-0.1.1.dist-info/METADATA
openthaigpt-0.1.1.dist-info/WHEEL
openthaigpt-0.1.1.dist-info/top_level.txt
openthaigpt-0.1.1.dist-info/RECORD
